{
    "questions": [
        {
            "id": 1,
            "question": "What is the purpose of an operating system?",
            "subject": "OS",
            "topic": "Introduction to OS",
            "difficulty": "easy",
            "marks": 1
        },
        {
            "id": 2,
            "question": "Explain the concept of process scheduling in operating systems.",
            "subject": "OS",
            "topic": "Process Scheduling",
            "difficulty": "medium",
            "marks": 2
        },
        {
            "id": 3,
            "question": "Discuss the role of a database management system (DBMS) in modern applications.",
            "subject": "DBMS",
            "topic": "Introduction to DBMS",
            "difficulty": "easy",
            "marks": 1
        },
        {
            "id": 4,
            "question": "Compare and contrast primary and foreign keys in a relational database.",
            "subject": "DBMS",
            "topic": "Keys in DBMS",
            "difficulty": "medium",
            "marks": 2
        },
        {
            "id": 5,
            "question": "Implement a stack using arrays in a programming language of your choice.",
            "subject": "DSA",
            "topic": "Stacks",
            "difficulty": "easy",
            "marks": 1
        },
        {
            "id": 6,
            "question": "Explain the concept of time complexity in algorithm analysis.",
            "subject": "DSA",
            "topic": "Time Complexity",
            "difficulty": "medium",
            "marks": 2
        },
        {
            "id": 7,
            "question": "Define and give an example of polymorphism in object-oriented programming.",
            "subject": "OOPs",
            "topic": "Polymorphism",
            "difficulty": "easy",
            "marks": 1
        },
        {
            "id": 8,
            "question": "Discuss the importance of encapsulation in software development.",
            "subject": "OOPs",
            "topic": "Encapsulation",
            "difficulty": "medium",
            "marks": 2
        },
        {
            "id": 9,
            "question": "What are the key principles of object-oriented design?",
            "subject": "OOPs",
            "topic": "OOP Design Principles",
            "difficulty": "easy",
            "marks": 1
        },
        {
            "id": 10,
            "question": "Explain the concept of file handling in operating systems.",
            "subject": "OS",
            "topic": "File Handling",
            "difficulty": "medium",
            "marks": 2
        },
        {
            "id": 11,
            "question": "Describe the role of virtual memory in operating systems.",
            "subject": "OS",
            "topic": "Virtual Memory",
            "difficulty": "hard",
            "marks": 3
        },
        {
            "id": 12,
            "question": "Explain the concept of normalization in database design.",
            "subject": "DBMS",
            "topic": "Normalization",
            "difficulty": "medium",
            "marks": 2
        },
        {
            "id": 13,
            "question": "Implement a binary search tree and perform an in-order traversal.",
            "subject": "DSA",
            "topic": "Binary Search Trees",
            "difficulty": "medium",
            "marks": 2
        },
        {
            "id": 14,
            "question": "Discuss the advantages and disadvantages of using linked lists in data structures.",
            "subject": "DSA",
            "topic": "Linked Lists",
            "difficulty": "hard",
            "marks": 3
        },
        {
            "id": 15,
            "question": "Explain the concept of inheritance in object-oriented programming with a practical example.",
            "subject": "OOPs",
            "topic": "Inheritance",
            "difficulty": "medium",
            "marks": 2
        },
        {
            "id": 16,
            "question": "What are the differences between abstraction and encapsulation in OOP?",
            "subject": "OOPs",
            "topic": "Abstraction",
            "difficulty": "hard",
            "marks": 3
        },
        {
            "id": 17,
            "question": "Discuss the role of the CPU scheduler in an operating system.",
            "subject": "OS",
            "topic": "CPU Scheduling",
            "difficulty": "medium",
            "marks": 2
        },
        {
            "id": 18,
            "question": "Explain the concept of indexing in database management.",
            "subject": "DBMS",
            "topic": "Indexing",
            "difficulty": "hard",
            "marks": 3
        },
        {
            "id": 19,
            "question": "Implement a queue data structure using a linked list.",
            "subject": "DSA",
            "topic": "Queues",
            "difficulty": "medium",
            "marks": 2
        },
        {
            "id": 20,
            "question": "Discuss the concept of transaction management in database systems.",
            "subject": "DBMS",
            "topic": "Transaction Management",
            "difficulty": "hard",
            "marks": 3
        },
        {
            "id": 21,
            "question": "Explain the role of the shell in operating systems.",
            "subject": "OS",
            "topic": "Operating System Shell",
            "difficulty": "easy",
            "marks": 1
        },
        {
            "id": 22,
            "question": "Compare and contrast SQL and NoSQL databases.",
            "subject": "DBMS",
            "topic": "SQL vs NoSQL",
            "difficulty": "medium",
            "marks": 2
        },
        {
            "id": 23,
            "question": "Implement a depth-first search algorithm for a graph.",
            "subject": "DSA",
            "topic": "Graph Algorithms",
            "difficulty": "medium",
            "marks": 2
        },
        {
            "id": 24,
            "question": "Discuss the concept of normalization in the context of databases.",
            "subject": "DBMS",
            "topic": "Normalization",
            "difficulty": "medium",
            "marks": 2
        },
        {
            "id": 25,
            "question": "Explain the principles of encapsulation with examples from OOP.",
            "subject": "OOPs",
            "topic": "Encapsulation",
            "difficulty": "medium",
            "marks": 2
        },
        {
            "id": 26,
            "question": "What is the purpose of the 'this' keyword in object-oriented programming?",
            "subject": "OOPs",
            "topic": "This Keyword",
            "difficulty": "easy",
            "marks": 1
        },
        {
            "id": 27,
            "question": "Discuss the role of an interrupt in operating systems.",
            "subject": "OS",
            "topic": "Interrupts",
            "difficulty": "medium",
            "marks": 2
        },
        {
            "id": 28,
            "question": "Explain the concept of deadlock in operating systems and how it can be avoided.",
            "subject": "OS",
            "topic": "Deadlocks",
            "difficulty": "hard",
            "marks": 3
        },
        {
            "id": 29,
            "question": "Describe the ACID properties in the context of database transactions.",
            "subject": "DBMS",
            "topic": "ACID Properties",
            "difficulty": "medium",
            "marks": 2
        },
        {
            "id": 30,
            "question": "Implement a priority queue using a heap data structure.",
            "subject": "DSA",
            "topic": "Priority Queues",
            "difficulty": "hard",
            "marks": 3
        },
        {
            "id": 31,
            "question": "Explain the concept of dynamic memory allocation in programming languages.",
            "subject": "DSA",
            "topic": "Dynamic Memory Allocation",
            "difficulty": "medium",
            "marks": 2
        },
        {
            "id": 32,
            "question": "Discuss the role of normalization in optimizing database performance.",
            "subject": "DBMS",
            "topic": "Normalization",
            "difficulty": "hard",
            "marks": 3
        },
        {
            "id": 33,
            "question": "Implement a breadth-first search algorithm for a graph.",
            "subject": "DSA",
            "topic": "Graph Algorithms",
            "difficulty": "medium",
            "marks": 2
        },
        {
            "id": 34,
            "question": "Explain the concept of 3-tier architecture in database systems.",
            "subject": "DBMS",
            "topic": "Database Architecture",
            "difficulty": "hard",
            "marks": 3
        },
        {
            "id": 35,
            "question": "Discuss the advantages of using polymorphism in object-oriented programming.",
            "subject": "OOPs",
            "topic": "Polymorphism",
            "difficulty": "medium",
            "marks": 2
        },
        {
            "id": 36,
            "question": "What are the key differences between procedural and object-oriented programming?",
            "subject": "OOPs",
            "topic": "Programming Paradigms",
            "difficulty": "hard",
            "marks": 3
        },
        {
            "id": 37,
            "question": "Explain the concept of demand paging in virtual memory management.",
            "subject": "OS",
            "topic": "Demand Paging",
            "difficulty": "medium",
            "marks": 2
        },
        {
            "id": 38,
            "question": "Discuss the role of triggers in database management systems.",
            "subject": "DBMS",
            "topic": "Database Triggers",
            "difficulty": "hard",
            "marks": 3
        },
        {
            "id": 39,
            "question": "Implement a hash table data structure in a programming language of your choice.",
            "subject": "DSA",
            "topic": "Hash Tables",
            "difficulty": "medium",
            "marks": 2
        },
        {
            "id": 40,
            "question": "Explain the concept of data warehousing and its significance in modern business intelligence.",
            "subject": "DBMS",
            "topic": "Data Warehousing",
            "difficulty": "hard",
            "marks": 3
        },
        {
            "id": 41,
            "question": "Discuss the role of the file system in operating systems.",
            "subject": "OS",
            "topic": "File System",
            "difficulty": "easy",
            "marks": 1
        },
        {
            "id": 42,
            "question": "Explain the concept of normalization in the context of database design.",
            "subject": "DBMS",
            "topic": "Normalization",
            "difficulty": "medium",
            "marks": 2
        },
        {
            "id": 43,
            "question": "Implement a binary search algorithm in a programming language of your choice.",
            "subject": "DSA",
            "topic": "Searching Algorithms",
            "difficulty": "medium",
            "marks": 2
        },
        {
            "id": 44,
            "question": "Discuss the advantages of using stored procedures in database systems.",
            "subject": "DBMS",
            "topic": "Stored Procedures",
            "difficulty": "medium",
            "marks": 2
        },
        {
            "id": 45,
            "question": "Explain the concept of interface in object-oriented programming.",
            "subject": "OOPs",
            "topic": "Interfaces",
            "difficulty": "easy",
            "marks": 1
        },
        {
            "id": 46,
            "question": "Discuss the role of page replacement algorithms in virtual memory management.",
            "subject": "OS",
            "topic": "Page Replacement Algorithms",
            "difficulty": "medium",
            "marks": 2
        },
        {
            "id": 47,
            "question": "Explain the concept of a foreign key in database management systems.",
            "subject": "DBMS",
            "topic": "Foreign Keys",
            "difficulty": "hard",
            "marks": 3
        },
        {
            "id": 48,
            "question": "Implement a merge sort algorithm in a programming language of your choice.",
            "subject": "DSA",
            "topic": "Sorting Algorithms",
            "difficulty": "medium",
            "marks": 2
        },
        {
            "id": 49,
            "question": "Discuss the role of constructors in object-oriented programming.",
            "subject": "OOPs",
            "topic": "Constructors",
            "difficulty": "medium",
            "marks": 2
        },
        {
            "id": 50,
            "question": "Explain the concept of process synchronization in operating systems.",
            "subject": "OS",
            "topic": "Process Synchronization",
            "difficulty": "hard",
            "marks": 3
        }
    ]
  }
  